ocaml/__init__.py
ocaml/sharedlib/arith_status.cmi
ocaml/sharedlib/big_int.cmi
ocaml/sharedlib/bigarray.cmi
ocaml/sharedlib/camlinternalFormat.cmi
ocaml/sharedlib/camlinternalFormatBasics.cmi
ocaml/sharedlib/camlinternalLazy.cmi
ocaml/sharedlib/camlinternalMod.cmi
ocaml/sharedlib/camlinternalOO.cmi
ocaml/sharedlib/dynlink.cmi
ocaml/sharedlib/nat.cmi
ocaml/sharedlib/num.cmi
ocaml/sharedlib/ocaml.so
ocaml/sharedlib/profiling.cmi
ocaml/sharedlib/ratio.cmi
ocaml/sharedlib/raw_spacetime_lib.cmi
ocaml/sharedlib/std_exit.cmi
ocaml/sharedlib/stdlib.cmi
ocaml/sharedlib/stdlib__arg.cmi
ocaml/sharedlib/stdlib__array.cmi
ocaml/sharedlib/stdlib__arrayLabels.cmi
ocaml/sharedlib/stdlib__bigarray.cmi
ocaml/sharedlib/stdlib__bool.cmi
ocaml/sharedlib/stdlib__buffer.cmi
ocaml/sharedlib/stdlib__bytes.cmi
ocaml/sharedlib/stdlib__bytesLabels.cmi
ocaml/sharedlib/stdlib__callback.cmi
ocaml/sharedlib/stdlib__char.cmi
ocaml/sharedlib/stdlib__complex.cmi
ocaml/sharedlib/stdlib__digest.cmi
ocaml/sharedlib/stdlib__ephemeron.cmi
ocaml/sharedlib/stdlib__filename.cmi
ocaml/sharedlib/stdlib__float.cmi
ocaml/sharedlib/stdlib__format.cmi
ocaml/sharedlib/stdlib__fun.cmi
ocaml/sharedlib/stdlib__gc.cmi
ocaml/sharedlib/stdlib__genlex.cmi
ocaml/sharedlib/stdlib__hashtbl.cmi
ocaml/sharedlib/stdlib__int.cmi
ocaml/sharedlib/stdlib__int32.cmi
ocaml/sharedlib/stdlib__int64.cmi
ocaml/sharedlib/stdlib__lazy.cmi
ocaml/sharedlib/stdlib__lexing.cmi
ocaml/sharedlib/stdlib__list.cmi
ocaml/sharedlib/stdlib__listLabels.cmi
ocaml/sharedlib/stdlib__map.cmi
ocaml/sharedlib/stdlib__marshal.cmi
ocaml/sharedlib/stdlib__moreLabels.cmi
ocaml/sharedlib/stdlib__nativeint.cmi
ocaml/sharedlib/stdlib__obj.cmi
ocaml/sharedlib/stdlib__oo.cmi
ocaml/sharedlib/stdlib__option.cmi
ocaml/sharedlib/stdlib__parsing.cmi
ocaml/sharedlib/stdlib__pervasives.cmi
ocaml/sharedlib/stdlib__pervasives.p.cmi
ocaml/sharedlib/stdlib__printexc.cmi
ocaml/sharedlib/stdlib__printf.cmi
ocaml/sharedlib/stdlib__queue.cmi
ocaml/sharedlib/stdlib__random.cmi
ocaml-0.0.11.dist-info/METADATA
ocaml-0.0.11.dist-info/WHEEL
ocaml-0.0.11.dist-info/top_level.txt
ocaml-0.0.11.dist-info/RECORD
